README.rst
setup.py
airwing_geoinfo/__init__.py
airwing_geoinfo/getgeoinfo.py
airwing_geoinfo.egg-info/PKG-INFO
airwing_geoinfo.egg-info/SOURCES.txt
airwing_geoinfo.egg-info/dependency_links.txt
airwing_geoinfo.egg-info/top_level.txt
airwing_geoinfo.egg-info/zip-safe