Metadata-Version: 1.1
Name: airwing-geoinfo
Version: 1.0.5
Summary: this is a package for getting geoinfo in geoserver
Home-page: https://github.com/surongxiang/airwing_geoinfo
Author: wushi
Author-email: hfutsrx@gmail.com
License: MIT
Keywords: geoserver python
Platform: UNKNOWN
Classifier: License :: OSI Approved :: MIT License
Classifier: Programming Language :: Python
Classifier: Intended Audience :: Developers
Classifier: Operating System :: MacOS :: MacOS X
